pdbfixer/__init__.py
pdbfixer/pdbfixer.py
pdbfixer/soft.xml
pdbfixer/ui.py
pdbfixer/uiserver.py
pdbfixer/html/addHeavyAtoms.html
pdbfixer/html/addHydrogens.html
pdbfixer/html/addResidues.html
pdbfixer/html/convertResidues.html
pdbfixer/html/error.html
pdbfixer/html/header.html
pdbfixer/html/quit.html
pdbfixer/html/removeChains.html
pdbfixer/html/saveFile.html
pdbfixer/html/start.html
pdbfixer/images/background.jpg
pdbfixer/images/logo.png
pdbfixer/images/logo_small.png
pdbfixer/templates/A.pdb
pdbfixer/templates/ACE.pdb
pdbfixer/templates/ALA.pdb
pdbfixer/templates/ARG.pdb
pdbfixer/templates/ASN.pdb
pdbfixer/templates/ASP.pdb
pdbfixer/templates/C.pdb
pdbfixer/templates/CYS.pdb
pdbfixer/templates/DA.pdb
pdbfixer/templates/DC.pdb
pdbfixer/templates/DG.pdb
pdbfixer/templates/DT.pdb
pdbfixer/templates/G.pdb
pdbfixer/templates/GLN.pdb
pdbfixer/templates/GLU.pdb
pdbfixer/templates/GLY.pdb
pdbfixer/templates/HIS.pdb
pdbfixer/templates/ILE.pdb
pdbfixer/templates/LEU.pdb
pdbfixer/templates/LYS.pdb
pdbfixer/templates/MET.pdb
pdbfixer/templates/NME.pdb
pdbfixer/templates/PHE.pdb
pdbfixer/templates/PRO.pdb
pdbfixer/templates/SER.pdb
pdbfixer/templates/THR.pdb
pdbfixer/templates/TRP.pdb
pdbfixer/templates/TYR.pdb
pdbfixer/templates/U.pdb
pdbfixer/templates/VAL.pdb
pdbfixer/tests/__init__.py
pdbfixer/tests/test_add_hydrogens.py
pdbfixer/tests/test_build_and_simulate.py
pdbfixer/tests/test_charge_and_solvate.py
pdbfixer/tests/test_cli.py
pdbfixer/tests/test_mutate.py
pdbfixer/tests/test_removechains.py
pdbfixer/tests/data/1BHL.pdb
pdbfixer/tests/data/4JSV.pdb
pdbfixer/tests/data/CAS.pdb
pdbfixer/tests/data/alanine-dipeptide.pdb
pdbfixer/tests/data/test.pdb
pdbfixer_wheel-1.12.4.dist-info/licenses/LICENSE
pdbfixer_wheel-1.12.4.dist-info/METADATA
pdbfixer_wheel-1.12.4.dist-info/WHEEL
pdbfixer_wheel-1.12.4.dist-info/entry_points.txt
pdbfixer_wheel-1.12.4.dist-info/top_level.txt
pdbfixer_wheel-1.12.4.dist-info/RECORD
