Metadata-Version: 2.4
Name: pdbfixer-wheel
Version: 1.12.4
Summary: Fork of pdbfixer (https://github.com/openmm/pdbfixer) to be able to pip install it.
Author: Peter Eastman, Abhishek Tiwari
License-Expression: MIT
Project-URL: Homepage, https://github.com/abhishektiwari/pdbfixer-wheel
Project-URL: Bug Tracker, https://github.com/abhishektiwari/pdbfixer-wheel/issues
Classifier: Development Status :: 5 - Production/Stable
Classifier: Intended Audience :: Science/Research
Classifier: Intended Audience :: Developers
Classifier: Programming Language :: Python
Classifier: Programming Language :: Python :: 3
Classifier: Programming Language :: Python :: 3.10
Classifier: Programming Language :: Python :: 3.11
Classifier: Programming Language :: Python :: 3.12
Classifier: Programming Language :: Python :: 3.13
Classifier: Topic :: Scientific/Engineering :: Bio-Informatics
Classifier: Topic :: Scientific/Engineering :: Chemistry
Classifier: Operating System :: Microsoft :: Windows
Classifier: Operating System :: POSIX
Classifier: Operating System :: Unix
Classifier: Operating System :: MacOS
Requires-Python: >=3.10
License-File: LICENSE
Requires-Dist: numpy
Requires-Dist: openmm>=8.1.1
Dynamic: license-file
